napari_tree_rings/__init__.py
napari_tree_rings/_sample_data.py
napari_tree_rings/_widget.py
napari_tree_rings/array_util.py
napari_tree_rings/napari.yaml
napari_tree_rings/progress.py
napari_tree_rings/qtutil.py
napari_tree_rings/_tests/__init__.py
napari_tree_rings/_tests/test_sample_data.py
napari_tree_rings/_tests/test_widget.py
napari_tree_rings/_tests/utils.py
napari_tree_rings/image/__init__.py
napari_tree_rings/image/fiji.py
napari_tree_rings/image/file_util.py
napari_tree_rings/image/measure.py
napari_tree_rings/image/process.py
napari_tree_rings/image/segmentation.py
napari_tree_rings/resources/gear.png
napari_tree_rings-0.1.5.dist-info/licenses/LICENSE
napari_tree_rings-0.1.5.dist-info/METADATA
napari_tree_rings-0.1.5.dist-info/WHEEL
napari_tree_rings-0.1.5.dist-info/entry_points.txt
napari_tree_rings-0.1.5.dist-info/top_level.txt
napari_tree_rings-0.1.5.dist-info/RECORD
