Metadata-Version: 2.4
Name: napari-tree-rings
Version: 0.1.5
Summary: A tool to delineate bark, pith and xylem annual rings and to measure their property parameters on circular sections of tree trunks.
Author: Volker Baecker, Thi-Thu-Khiet Dang
Author-email: volker.baecker@mri.cnrs.fr, dangthithukhiet7988@gmail.com
License: MIT License
Classifier: Development Status :: 2 - Pre-Alpha
Classifier: Framework :: napari
Classifier: Intended Audience :: Developers
Classifier: License :: OSI Approved :: MIT License
Classifier: Operating System :: OS Independent
Classifier: Programming Language :: Python
Classifier: Programming Language :: Python :: 3
Classifier: Programming Language :: Python :: 3 :: Only
Classifier: Programming Language :: Python :: 3.9
Classifier: Programming Language :: Python :: 3.10
Classifier: Programming Language :: Python :: 3.11
Classifier: Programming Language :: Python :: 3.12
Classifier: Topic :: Scientific/Engineering :: Image Processing
Requires-Python: >=3.9
License-File: LICENSE
Requires-Dist: brightest-path-lib
Requires-Dist: tree-ring-analyzer
Requires-Dist: numpy
Requires-Dist: magicgui
Requires-Dist: qtpy
Requires-Dist: scikit-image
Requires-Dist: appdirs
Requires-Dist: scyjava
Requires-Dist: pyperclip
Requires-Dist: shapelysmooth
Requires-Dist: imagej
Requires-Dist: napari-imagej
Requires-Dist: scikit-learn
Requires-Dist: torch
Requires-Dist: torchvision
Requires-Dist: matplotlib
Requires-Dist: opencv-python-headless
Requires-Dist: pint
Requires-Dist: tifffile
Requires-Dist: tensorflow==2.17.0
Requires-Dist: python-polylabel
Provides-Extra: testing
Requires-Dist: tox; extra == "testing"
Requires-Dist: pytest; extra == "testing"
Requires-Dist: pytest-cov; extra == "testing"
Requires-Dist: pytest-qt; extra == "testing"
Requires-Dist: napari; extra == "testing"
Requires-Dist: pyqt5; extra == "testing"
Requires-Dist: qtpy; extra == "testing"
Requires-Dist: tree-ring-analyzer; extra == "testing"
Requires-Dist: matplotlib; extra == "testing"
Requires-Dist: brightest-path-lib; extra == "testing"
Requires-Dist: numpy; extra == "testing"
Requires-Dist: scikit-image; extra == "testing"
Requires-Dist: opencv-python-headless; extra == "testing"
Requires-Dist: pint; extra == "testing"
Requires-Dist: tifffile; extra == "testing"
Requires-Dist: tensorflow==2.17.0; extra == "testing"
Requires-Dist: python-polylabel; extra == "testing"
Requires-Dist: scikit-learn; extra == "testing"
Provides-Extra: docs
Requires-Dist: sphinx_rtd_theme; extra == "docs"
Requires-Dist: myst_parser; extra == "docs"
Requires-Dist: sphinx_tabs; extra == "docs"
Requires-Dist: sphinx; extra == "docs"
Dynamic: license-file
